Workbook

Sheet Ventas
A1: AUTOMALL · CONTROL DE VENTAS
A2: ID | B2: INFO | C2: CLIENTE | H2: VEHÍCULO | N2: FINANCIERO | Q2: PICK PAYMENT | V2: CALENDARIO DE PAGOS | AH2: RESUMEN | AJ2: ADICIONAL
A3: # | B3: FECHA VENTA | C3: NOMBRE CLIENTE | D3: TELÉFONO | E3: EMAIL | F3: REFERIDO POR | G3: FUENTE | H3: MARCA | I3: MODELO | J3: AÑO | K3: COLOR | L3: VIN | M3: MILLAJE | N3: PRECIO VENTA | O3: ENGANCHE | P3: MONTO FINANCIADO | Q3: PICK PAYMENT | R3: # CUOTAS | S3: 1er PAGO (FECHA) | T3: DÍA DE PAGO | U3: CUOTA SEMANAL | V3: PAGO 1 FECHA | W3: P1 ESTATUS | X3: PAGO 2 FECHA | Y3: P2 ESTATUS | Z3: PAGO 3 FECHA | AA3: P3 ESTATUS | AB3: PAGO 4 FECHA | AC3: P4 ESTATUS | AD3: PAGO 5 FECHA | AE3: P5 ESTATUS | AF3: PAGO 6 FECHA | AG3: P6 ESTATUS | AH3: TOTAL COBRADO | AI3: SALDO PENDIENTE | AJ3: FINANCIERA / BANCO | AK3: GPS INSTAL. | AL3: ESTATUS DEAL | AM3: COMISIÓN | AN3: NOTAS
A4: =IF(C4<>"",ROW()-3,"") | B4: 01/15/2026 | C4: María García (EJEMPLO) | D4: (713) 555-0100 | E4: mgarcia@email.com | F4: Juan López | G4: REFERIDO | H4: Toyota | I4: Camry | J4: 2022 | K4: Blanco | L4: 1HGBH41JXMN109186 | M4: 45000 | N4: 18500 | O4: 2000 | P4: =IF(AND(Q4="SÍ",N4<>"",O4<>""),N4-O4,"") | Q4: SÍ | R4: 6 | S4: 01/22/2026 | T4: =IF(S4<>"",CHOOSE(WEEKDAY(S4,2),"Lunes","Martes","Miércoles","Jueves","Viernes","Sábado","Domingo"),"") | U4: =IF(AND(P4<>"",R4>0),ROUND(P4/R4,2),"") | V4: =IF(AND(Q4="SÍ",S4<>""),S4,"") | W4: PAGADO | X4: =IF(V4<>"",V4+7,"") | Y4: PAGADO | Z4: =IF(X4<>"",X4+7,"") | AA4: PENDIENTE | AB4: =IF(Z4<>"",Z4+7,"") | AD4: =IF(AB4<>"",AB4+7,"") | AF4: =IF(AD4<>"",AD4+7,"") | AH4: =IF(U4<>"",(COUNTIF(W4,"PAGADO")+COUNTIF(Y4,"PAGADO")+COUNTIF(AA4,"PAGADO")+COUNTIF(AC4,"PAGADO")+COUNTIF(AE4,"PAGADO")+COUNTIF(AG4,"PAGADO"))*U4,"") | AI4: =IF(AND(P4<>"",AH4<>""),P4-AH4,IF(P4<>"",P4,"")) | AJ4: Westlake Financial | AK4: SÍ | AL4: ACTIVO | AM4: 750 | AN4: Cliente de referido de Juan López. Trade-in: Honda Civic 2018.
A5: =IF(C5<>"",ROW()-3,"") | P5: =IF(AND(Q5="SÍ",N5<>"",O5<>""),N5-O5,"") | T5: =IF(S5<>"",CHOOSE(WEEKDAY(S5,2),"Lunes","Martes","Miércoles","Jueves","Viernes","Sábado","Domingo"),"") | U5: =IF(AND(P5<>"",R5>0),ROUND(P5/R5,2),"") | V5: =IF(AND(Q5="SÍ",S5<>""),S5,"") | X5: =IF(V5<>"",V5+7,"") | Z5: =IF(X5<>"",X5+7,"") | AB5: =IF(Z5<>"",Z5+7,"") | AD5: =IF(AB5<>"",AB5+7,"") | AF5: =IF(AD5<>"",AD5+7,"") | AH5: =IF(U5<>"",(COUNTIF(W5,"PAGADO")+COUNTIF(Y5,"PAGADO")+COUNTIF(AA5,"PAGADO")+COUNTIF(AC5,"PAGADO")+COUNTIF(AE5,"PAGADO")+COUNTIF(AG5,"PAGADO"))*U5,"") | AI5: =IF(AND(P5<>"",AH5<>""),P5-AH5,IF(P5<>"",P5,""))
A6: =IF(C6<>"",ROW()-3,"") | P6: =IF(AND(Q6="SÍ",N6<>"",O6<>""),N6-O6,"") | T6: =IF(S6<>"",CHOOSE(WEEKDAY(S6,2),"Lunes","Martes","Miércoles","Jueves","Viernes","Sábado","Domingo"),"") | U6: =IF(AND(P6<>"",R6>0),ROUND(P6/R6,2),"") | V6: =IF(AND(Q6="SÍ",S6<>""),S6,"") | X6: =IF(V6<>"",V6+7,"") | Z6: =IF(X6<>"",X6+7,"") | AB6: =IF(Z6<>"",Z6+7,"") | AD6: =IF(AB6<>"",AB6+7,"") | AF6: =IF(AD6<>"",AD6+7,"") | AH6: =IF(U6<>"",(COUNTIF(W6,"PAGADO")+COUNTIF(Y6,"PAGADO")+COUNTIF(AA6,"PAGADO")+COUNTIF(AC6,"PAGADO")+COUNTIF(AE6,"PAGADO")+COUNTIF(AG6,"PAGADO"))*U6,"") | AI6: =IF(AND(P6<>"",AH6<>""),P6-AH6,IF(P6<>"",P6,""))
A7: =IF(C7<>"",ROW()-3,"") | P7: =IF(AND(Q7="SÍ",N7<>"",O7<>""),N7-O7,"") | T7: =IF(S7<>"",CHOOSE(WEEKDAY(S7,2),"Lunes","Martes","Miércoles","Jueves","Viernes","Sábado","Domingo"),"") | U7: =IF(AND(P7<>"",R7>0),ROUND(P7/R7,2),"") | V7: =IF(AND(Q7="SÍ",S7<>""),S7,"") | X7: =IF(V7<>"",V7+7,"") | Z7: =IF(X7<>"",X7+7,"") | AB7: =IF(Z7<>"",Z7+7,"") | AD7: =IF(AB7<>"",AB7+7,"") | AF7: =IF(AD7<>"",AD7+7,"") | AH7: =IF(U7<>"",(COUNTIF(W7,"PAGADO")+COUNTIF(Y7,"PAGADO")+COUNTIF(AA7,"PAGADO")+COUNTIF(AC7,"PAGADO")+COUNTIF(AE7,"PAGADO")+COUNTIF(AG7,"PAGADO"))*U7,"") | AI7: =IF(AND(P7<>"",AH7<>""),P7-AH7,IF(P7<>"",P7,""))
A8: =IF(C8<>"",ROW()-3,"") | P8: =IF(AND(Q8="SÍ",N8<>"",O8<>""),N8-O8,"") | T8: =IF(S8<>"",CHOOSE(WEEKDAY(S8,2),"Lunes","Martes","Miércoles","Jueves","Viernes","Sábado","Domingo"),"") | U8: =IF(AND(P8<>"",R8>0),ROUND(P8/R8,2),"") | V8: =IF(AND(Q8="SÍ",S8<>""),S8,"") | X8: =IF(V8<>"",V8+7,"") | Z8: =IF(X8<>"",X8+7,"") | AB8: =IF(Z8<>"",Z8+7,"") | AD8: =IF(AB8<>"",AB8+7,"") | AF8: =IF(AD8<>"",AD8+7,"") | AH8: =IF(U8<>"",(COUNTIF(W8,"PAGADO")+COUNTIF(Y8,"PAGADO")+COUNTIF(AA8,"PAGADO")+COUNTIF(AC8,"PAGADO")+COUNTIF(AE8,"PAGADO")+COUNTIF(AG8,"PAGADO"))*U8,"") | AI8: =IF(AND(P8<>"",AH8<>""),P8-AH8,IF(P8<>"",P8,""))
A9: =IF(C9<>"",ROW()-3,"") | P9: =IF(AND(Q9="SÍ",N9<>"",O9<>""),N9-O9,"") | T9: =IF(S9<>"",CHOOSE(WEEKDAY(S9,2),"Lunes","Martes","Miércoles","Jueves","Viernes","Sábado","Domingo"),"") | U9: =IF(AND(P9<>"",R9>0),ROUND(P9/R9,2),"") | V9: =IF(AND(Q9="SÍ",S9<>""),S9,"") | X9: =IF(V9<>"",V9+7,"") | Z9: =IF(X9<>"",X9+7,"") | AB9: =IF(Z9<>"",Z9+7,"") | AD9: =IF(AB9<>"",AB9+7,"") | AF9: =IF(AD9<>"",AD9+7,"") | AH9: =IF(U9<>"",(COUNTIF(W9,"PAGADO")+COUNTIF(Y9,"PAGADO")+COUNTIF(AA9,"PAGADO")+COUNTIF(AC9,"PAGADO")+COUNTIF(AE9,"PAGADO")+COUNTIF(AG9,"PAGADO"))*U9,"") | AI9: =IF(AND(P9<>"",AH9<>""),P9-AH9,IF(P9<>"",P9,""))
A10: =IF(C10<>"",ROW()-3,"") | P10: =IF(AND(Q10="SÍ",N10<>"",O10<>""),N10-O10,"") | T10: =IF(S10<>"",CHOOSE(WEEKDAY(S10,2),"Lunes","Martes","Miércoles","Jueves","Viernes","Sábado","Domingo"),"") | U10: =IF(AND(P10<>"",R10>0),ROUND(P10/R10,2),"") | V10: =IF(AND(Q10="SÍ",S10<>""),S10,"") | X10: =IF(V10<>"",V10+7,"") | Z10: =IF(X10<>"",X10+7,"") | AB10: =IF(Z10<>"",Z10+7,"") | AD10: =IF(AB10<>"",AB10+7,"") | AF10: =IF(AD10<>"",AD10+7,"") | AH10: =IF(U10<>"",(COUNTIF(W10,"PAGADO")+COUNTIF(Y10,"PAGADO")+COUNTIF(AA10,"PAGADO")+COUNTIF(AC10,"PAGADO")+COUNTIF(AE10,"PAGADO")+COUNTIF(AG10,"PAGADO"))*U10,"") | AI10: =IF(AND(P10<>"",AH10<>""),P10-AH10,IF(P10<>"",P10,""))
A11: =IF(C11<>"",ROW()-3,"") | P11: =IF(AND(Q11="SÍ",N11<>"",O11<>""),N11-O11,"") | T11: =IF(S11<>"",CHOOSE(WEEKDAY(S11,2),"Lunes","Martes","Miércoles","Jueves","Viernes","Sábado","Domingo"),"") | U11: =IF(AND(P11<>"",R11>0),ROUND(P11/R11,2),"") | V11: =IF(AND(Q11="SÍ",S11<>""),S11,"") | X11: =IF(V11<>"",V11+7,"") | Z11: =IF(X11<>"",X11+7,"") | AB11: =IF(Z11<>"",Z11+7,"") | AD11: =IF(AB11<>"",AB11+7,"") | AF11: =IF(AD11<>"",AD11+7,"") | AH11: =IF(U11<>"",(COUNTIF(W11,"PAGADO")+COUNTIF(Y11,"PAGADO")+COUNTIF(AA11,"PAGADO")+COUNTIF(AC11,"PAGADO")+COUNTIF(AE11,"PAGADO")+COUNTIF(AG11,"PAGADO"))*U11,"") | AI11: =IF(AND(P11<>"",AH11<>""),P11-AH11,IF(P11<>"",P11,""))
A12: =IF(C12<>"",ROW()-3,"") | P12: =IF(AND(Q12="SÍ",N12<>"",O12<>""),N12-O12,"") | T12: =IF(S12<>"",CHOOSE(WEEKDAY(S12,2),"Lunes","Martes","Miércoles","Jueves","Viernes","Sábado","Domingo"),"") | U12: =IF(AND(P12<>"",R12>0),ROUND(P12/R12,2),"") | V12: =IF(AND(Q12="SÍ",S12<>""),S12,"") | X12: =IF(V12<>"",V12+7,"") | Z12: =IF(X12<>"",X12+7,"") | AB12: =IF(Z12<>"",Z12+7,"") | AD12: =IF(AB12<>"",AB12+7,"") | AF12: =IF(AD12<>"",AD12+7,"") | AH12: =IF(U12<>"",(COUNTIF(W12,"PAGADO")+COUNTIF(Y12,"PAGADO")+COUNTIF(AA12,"PAGADO")+COUNTIF(AC12,"PAGADO")+COUNTIF(AE12,"PAGADO")+COUNTIF(AG12,"PAGADO"))*U12,"") | AI12: =IF(AND(P12<>"",AH12<>""),P12-AH12,IF(P12<>"",P12,""))
A13: =IF(C13<>"",ROW()-3,"") | P13: =IF(AND(Q13="SÍ",N13<>"",O13<>""),N13-O13,"") | T13: =IF(S13<>"",CHOOSE(WEEKDAY(S13,2),"Lunes","Martes","Miércoles","Jueves","Viernes","Sábado","Domingo"),"") | U13: =IF(AND(P13<>"",R13>0),ROUND(P13/R13,2),"") | V13: =IF(AND(Q13="SÍ",S13<>""),S13,"") | X13: =IF(V13<>"",V13+7,"") | Z13: =IF(X13<>"",X13+7,"") | AB13: =IF(Z13<>"",Z13+7,"") | AD13: =IF(AB13<>"",AB13+7,"") | AF13: =IF(AD13<>"",AD13+7,"") | AH13: =IF(U13<>"",(COUNTIF(W13,"PAGADO")+COUNTIF(Y13,"PAGADO")+COUNTIF(AA13,"PAGADO")+COUNTIF(AC13,"PAGADO")+COUNTIF(AE13,"PAGADO")+COUNTIF(AG13,"PAGADO"))*U13,"") | AI13: =IF(AND(P13<>"",AH13<>""),P13-AH13,IF(P13<>"",P13,""))
A14: =IF(C14<>"",ROW()-3,"") | P14: =IF(AND(Q14="SÍ",N14<>"",O14<>""),N14-O14,"") | T14: =IF(S14<>"",CHOOSE(WEEKDAY(S14,2),"Lunes","Martes","Miércoles","Jueves","Viernes","Sábado","Domingo"),"") | U14: =IF(AND(P14<>"",R14>0),ROUND(P14/R14,2),"") | V14: =IF(AND(Q14="SÍ",S14<>""),S14,"") | X14: =IF(V14<>"",V14+7,"") | Z14: =IF(X14<>"",X14+7,"") | AB14: =IF(Z14<>"",Z14+7,"") | AD14: =IF(AB14<>"",AB14+7,"") | AF14: =IF(AD14<>"",AD14+7,"") | AH14: =IF(U14<>"",(COUNTIF(W14,"PAGADO")+COUNTIF(Y14,"PAGADO")+COUNTIF(AA14,"PAGADO")+COUNTIF(AC14,"PAGADO")+COUNTIF(AE14,"PAGADO")+COUNTIF(AG14,"PAGADO"))*U14,"") | AI14: =IF(AND(P14<>"",AH14<>""),P14-AH14,IF(P14<>"",P14,""))
A15: =IF(C15<>"",ROW()-3,"") | P15: =IF(AND(Q15="SÍ",N15<>"",O15<>""),N15-O15,"") | T15: =IF(S15<>"",CHOOSE(WEEKDAY(S15,2),"Lunes","Martes","Miércoles","Jueves","Viernes","Sábado","Domingo"),"") | U15: =IF(AND(P15<>"",R15>0),ROUND(P15/R15,2),"") | V15: =IF(AND(Q15="SÍ",S15<>""),S15,"") | X15: =IF(V15<>"",V15+7,"") | Z15: =IF(X15<>"",X15+7,"") | AB15: =IF(Z15<>"",Z15+7,"") | AD15: =IF(AB15<>"",AB15+7,"") | AF15: =IF(AD15<>"",AD15+7,"") | AH15: =IF(U15<>"",(COUNTIF(W15,"PAGADO")+COUNTIF(Y15,"PAGADO")+COUNTIF(AA15,"PAGADO")+COUNTIF(AC15,"PAGADO")+COUNTIF(AE15,"PAGADO")+COUNTIF(AG15,"PAGADO"))*U15,"") | AI15: =IF(AND(P15<>"",AH15<>""),P15-AH15,IF(P15<>"",P15,""))
A16: =IF(C16<>"",ROW()-3,"") | P16: =IF(AND(Q16="SÍ",N16<>"",O16<>""),N16-O16,"") | T16: =IF(S16<>"",CHOOSE(WEEKDAY(S16,2),"Lunes","Martes","Miércoles","Jueves","Viernes","Sábado","Domingo"),"") | U16: =IF(AND(P16<>"",R16>0),ROUND(P16/R16,2),"") | V16: =IF(AND(Q16="SÍ",S16<>""),S16,"") | X16: =IF(V16<>"",V16+7,"") | Z16: =IF(X16<>"",X16+7,"") | AB16: =IF(Z16<>"",Z16+7,"") | AD16: =IF(AB16<>"",AB16+7,"") | AF16: =IF(AD16<>"",AD16+7,"") | AH16: =IF(U16<>"",(COUNTIF(W16,"PAGADO")+COUNTIF(Y16,"PAGADO")+COUNTIF(AA16,"PAGADO")+COUNTIF(AC16,"PAGADO")+COUNTIF(AE16,"PAGADO")+COUNTIF(AG16,"PAGADO"))*U16,"") | AI16: =IF(AND(P16<>"",AH16<>""),P16-AH16,IF(P16<>"",P16,""))
... A153: =IF(C153<>"",ROW()-3,"") | P153: =IF(AND(Q153="SÍ",N153<>"",O153<>""),N153-O153,"") | T153: =IF(S153<>"",CHOOSE(WEEKDAY(S153,2),"Lunes","Martes","Miércoles","Jueves","Viernes","Sábado","Domingo"),"") | U153: =IF(AND(P153<>"",R153>0),ROUND(P153/R153,2),"") | V153: =IF(AND(Q153="SÍ",S153<>""),S153,"") | X153: =IF(V153<>"",V153+7,"") | Z153: =IF(X153<>"",X153+7,"") | AB153: =IF(Z153<>"",Z153+7,"") | AD153: =IF(AB153<>"",AB153+7,"") | AF153: =IF(AD153<>"",AD153+7,"") | AH153: =IF(U153<>"",(COUNTIF(W153,"PAGADO")+COUNTIF(Y153,"PAGADO")+COUNTIF(AA153,"PAGADO")+COUNTIF(AC153,"PAGADO")+COUNTIF(AE153,"PAGADO")+COUNTIF(AG153,"PAGADO"))*U153,"") | AI153: =IF(AND(P153<>"",AH153<>""),P153-AH153,IF(P153<>"",P153,""))
A155: TOTALES | N155: =SUM(N4:N153) | O155: =SUM(O4:O153) | P155: =SUM(P4:P153) | AH155: =SUM(AH4:AH153) | AI155: =SUM(AI4:AI153) | AM155: =SUM(AM4:AM153)

Sheet Dashboard
A1: AUTOMALL · DASHBOARD DE VENTAS
A2: Los números se actualizan automáticamente desde la hoja 'Ventas'
B4: TOTAL VENTAS | C4: PICK PAYMENT | D4: VENTAS ACTIVAS | E4: TOTAL VENDIDO (PRECIO) | F4: TOTAL COBRADO
B5: =COUNTA(Ventas!C4:C153) | C5: =COUNTIF(Ventas!Q4:Q153,"SÍ") | D5: =COUNTIF(Ventas!AL4:AL153,"ACTIVO") | E5: =SUM(Ventas!N4:N153) | F5: =SUM(Ventas!AH4:AH153)
B7: MÉTRICA | D7: VALOR
B8: Deals PAGADOS COMPLETO | D8: =COUNTIF(Ventas!AL4:AL153,"PAGADO COMPLETO")
B9: Deals EN REPO | D9: =COUNTIF(Ventas!AL4:AL153,"EN REPO")
B10: Deals CANCELADOS | D10: =COUNTIF(Ventas!AL4:AL153,"CANCELADO")
B11: Saldo Total PENDIENTE | D11: =SUM(Ventas!AI4:AI153)
B12: Total COMISIONES | D12: =SUM(Ventas!AM4:AM153)
B13: Pagos VENCIDOS (total) | D13: =COUNTIF(Ventas!W4:AG153,"VENCIDO")
B14: Pagos PENDIENTES | D14: =COUNTIF(Ventas!W4:AG153,"PENDIENTE")
B15: Precio Promedio por Venta | D15: =IFERROR(AVERAGE(Ventas!N4:N153),0)
B16: Enganche Promedio | D16: =IFERROR(AVERAGE(Ventas!O4:O153),0)

Sheet Instrucciones
A1: AUTOMALL · GUÍA DE USO
B3: COLUMNAS AUTOMÁTICAS | C3: Estas columnas se calculan solas — NO las edites manualmente:
B4: Monto Financiado (P) | C4: =Precio Venta − Enganche (solo si Pick Payment = SÍ)
B5: Día de Pago (T) | C5: =Día de semana del 1er pago (Lunes, Martes…) — calculado automático
B6: Cuota Semanal (U) | C6: =Monto Financiado ÷ # Cuotas
B7: Fechas Pago 2–6 (X,Z,AB,AD,AF) | C7: =Fecha anterior + 7 días (mismo día de la semana siempre)
B8: Total Cobrado (AH) | C8: =Suma de cuotas marcadas como PAGADO
B9: Saldo Pendiente (AI) | C9: =Monto Financiado − Total Cobrado
B11: CÓMO REGISTRAR UNA VENTA | C11: Sigue estos pasos en orden:
B12: Paso 1 — Fecha | C12: Ingresa la fecha de la venta en columna B (formato MM/DD/AAAA)
B13: Paso 2 — Cliente | C13: Llena nombre, teléfono, email, referido por, y fuente (dropdown)
B14: Paso 3 — Vehículo | C14: Marca, modelo, año, color, VIN, y millaje
B15: Paso 4 — Precio y Enganche | C15: Ingresa precio de venta y enganche en columnas N y O
B16: Paso 5 — Pick Payment | C16: Selecciona SÍ o NO en columna Q. Si es SÍ, ingresa # cuotas (default 6) y la fecha del 1er pago
B17: Paso 6 — Pagos semanales | C17: Las fechas de pago se calculan automáticamente. Solo cambia el ESTATUS cuando el cliente pague: PAGADO / VENCIDO / NO PAGÓ / PENDIENTE
B18: Paso 7 — Cierre | C18: Cuando se complete, cambia Estatus Deal a PAGADO COMPLETO
B20: COLORES DE REFERENCIA | C20: Significado de colores en columnas de estatus:
B21: Verde claro | C21: PAGADO — El cliente realizó el pago correctamente
B22: Rojo claro | C22: VENCIDO — La fecha de pago pasó y no pagó
B23: Rojo oscuro | C23: NO PAGÓ — Se confirmó que no va a pagar
... B31: Backup | C31: Guarda una copia del archivo al final de cada semana

Sheet Catálogos
A1: CATÁLOGOS — Listas de referencia para el Excel
B3: MARCAS DE AUTOS | C3: FUENTES DE VENTA | D3: FINANCIERAS / BANCOS | E3: REFERIDOS FRECUENTES
B4: Toyota | C4: REFERIDO | D4: Cash (Contado) | E4: — Agregar nombres aquí —
B5: Ford | C5: WALK-IN | D5: DriveTime | E5: (Ejemplo: Juan Pérez)
B6: Chevrolet | C6: INTERNET | D6: CarMax Auto Finance | E6: (Ejemplo: María García)
B7: Nissan | C7: REPEAT | D7: Westlake Financial | E7: (Ejemplo: Carlos López)
B8: GMC | C8: REDES SOCIALES | D8: Ally Financial
B9: Dodge | C9: ANUNCIO | D9: Capital One Auto
B10: Jeep | C10: CRAIGSLIST | D10: CUDL
B11: Mazda | C11: FACEBOOK MARKETPLACE | D11: CAC (Credit Acceptance)
B12: Mercedes-Benz | C12: OTRO | D12: JM Family
B13: Honda | D13: Santander Consumer
B14: Hyundai | D14: TD Auto Finance
B15: Kia | D15: Exeter Finance
B16: BMW | D16: AmeriCredit (GM Financial)
B17: Volkswagen | D17: Southeast Toyota Finance
B18: Chrysler | D18: Otro
B19: RAM
B20: Cadillac
B21: Buick
B22: Lincoln
B23: Acura
B24: Subaru
B25: Mitsubishi
B26: Lexus
B27: Audi
B28: Infiniti
